__init__.py
data_preprocess.py
differential_fit.py
zmodel.py
rchecks/__init__.py
rchecks/binning_v1.5.json
rchecks/binning_v1.6.json
rchecks/binning_v1.7.json
rchecks/binning_v1.8.json
rchecks/binning_v1.9.json
rx_differential_crosscheck_fits-0.0.6.dist-info/METADATA
rx_differential_crosscheck_fits-0.0.6.dist-info/WHEEL
rx_differential_crosscheck_fits-0.0.6.dist-info/top_level.txt
rx_differential_crosscheck_fits-0.0.6.dist-info/RECORD
