Metadata-Version: 2.1
Name: rx_differential_crosscheck_fits
Version: 0.0.6
Summary: Code used to fit jpsi and psi2S mode in bins of different variables
Requires-Dist: pandas
Requires-Dist: matplotlib
Requires-Dist: scipy
Requires-Dist: rx-scripts >=0.1.1
Requires-Dist: rx-selection >=0.0.3
Requires-Dist: rx-tools >=0.0.7
